CHANGES.rst
LICENSE
MANIFEST.in
README.rst
setup.py
dwebsocket/__init__.py
dwebsocket/decorators.py
dwebsocket/factory.py
dwebsocket/middleware.py
dwebsocket/websocket.py
dwebsocket.egg-info/PKG-INFO
dwebsocket.egg-info/SOURCES.txt
dwebsocket.egg-info/dependency_links.txt
dwebsocket.egg-info/requires.txt
dwebsocket.egg-info/top_level.txt
dwebsocket.egg-info/zip-safe
dwebsocket/backends/__init__.py
dwebsocket/backends/default/__init__.py
dwebsocket/backends/default/factory.py
dwebsocket/backends/default/protocols.py
dwebsocket/backends/default/websocket.py
dwebsocket/backends/uwsgi/__init__.py
dwebsocket/backends/uwsgi/factory.py
examples/manage.py
examples/run_eventlet.py
examples/examples/__init__.py
examples/examples/settings.py
examples/examples/urls.py
examples/examples/wsgi.py
examples/examples/templates/index.html