Metadata-Version: 1.1
Name: dwebsocket
Version: 0.5.5
Summary: Websocket support for django.
Home-page: http://github.com/duanhongyi/dwebsocket
Author: duanhongyi
Author-email: duanhongyi@github.com
License: BSD
Platform: UNKNOWN
Classifier: Development Status :: 5 - Production/Stable
Classifier: Environment :: Web Environment
Classifier: Framework :: Django
Classifier: Intended Audience :: Developers
Classifier: License :: OSI Approved :: BSD License
Classifier: Operating System :: OS Independent
Classifier: Programming Language :: Python
Classifier: Topic :: Software Development :: Libraries :: Python Modules
Classifier: Topic :: Utilities
